binance_info/__init__.py
binance_info/main.py
binance_info-2.0.dist-info/METADATA
binance_info-2.0.dist-info/WHEEL
binance_info-2.0.dist-info/top_level.txt
binance_info-2.0.dist-info/RECORD
