Metadata-Version: 2.1
Name: binance_info
Version: 2.0
Requires-Dist: requests
Requires-Dist: qrcode
Requires-Dist: pyotp
